{
  "status": "done",
  "assets": {
    "bundle.css": {
      "name": "bundle.css",
      "path": "/home/pinco/Desktop/MS4/digicreche/frontend/dist/bundle.css",
      "publicPath": "http://0.0.0.0:8080/bundle.css"
    },
    "bundle.js": {
      "name": "bundle.js",
      "path": "/home/pinco/Desktop/MS4/digicreche/frontend/dist/bundle.js",
      "publicPath": "http://0.0.0.0:8080/bundle.js"
    },
    "index.html": {
      "name": "index.html",
      "path": "/home/pinco/Desktop/MS4/digicreche/frontend/dist/index.html",
      "publicPath": "http://0.0.0.0:8080/index.html"
    },
    "app.1c7bc8cae18a6590394c.hot-update.js": {
      "name": "app.1c7bc8cae18a6590394c.hot-update.js",
      "path": "/home/pinco/Desktop/MS4/digicreche/frontend/dist/app.1c7bc8cae18a6590394c.hot-update.js",
      "publicPath": "http://0.0.0.0:8080/app.1c7bc8cae18a6590394c.hot-update.js"
    },
    "1c7bc8cae18a6590394c.hot-update.json": {
      "name": "1c7bc8cae18a6590394c.hot-update.json",
      "path": "/home/pinco/Desktop/MS4/digicreche/frontend/dist/1c7bc8cae18a6590394c.hot-update.json",
      "publicPath": "http://0.0.0.0:8080/1c7bc8cae18a6590394c.hot-update.json"
    },
    "app.edf6740941e2803e6c29.hot-update.js": {
      "name": "app.edf6740941e2803e6c29.hot-update.js",
      "path": "/home/pinco/Desktop/MS4/digicreche/frontend/dist/app.edf6740941e2803e6c29.hot-update.js",
      "publicPath": "http://0.0.0.0:8080/app.edf6740941e2803e6c29.hot-update.js"
    },
    "edf6740941e2803e6c29.hot-update.json": {
      "name": "edf6740941e2803e6c29.hot-update.json",
      "path": "/home/pinco/Desktop/MS4/digicreche/frontend/dist/edf6740941e2803e6c29.hot-update.json",
      "publicPath": "http://0.0.0.0:8080/edf6740941e2803e6c29.hot-update.json"
    }
  },
  "chunks": {
    "app": [
      "bundle.css",
      "bundle.js",
      "app.edf6740941e2803e6c29.hot-update.js"
    ]
  },
  "publicPath": "http://0.0.0.0:8080/"
}